spomato/__init__.py
spomato/spomato.py
spomato-0.2.0.dist-info/LICENSE.txt
spomato-0.2.0.dist-info/METADATA
spomato-0.2.0.dist-info/WHEEL
spomato-0.2.0.dist-info/top_level.txt
spomato-0.2.0.dist-info/RECORD
