Metadata-Version: 2.1
Name: spomato
Version: 0.2.0
Summary: Tomato Timer with Spotify
Home-page: https://github.com/pm8k/spomato
Author: Matthew Russell
Author-email: astromars42@gmail.com
License: MIT
Download-URL: https://github.com/pm8k/spomato/archive/0.2.0.tar.gz
Keywords: python,spotify,spotipy,tomato,timer,music
Platform: UNKNOWN
Requires-Dist: pandas
Requires-Dist: spotipy
